pipeline_material/__init__.py
pipeline_material-1.0.dist-info/LICENSE
pipeline_material-1.0.dist-info/METADATA
pipeline_material-1.0.dist-info/WHEEL
pipeline_material-1.0.dist-info/top_level.txt
pipeline_material-1.0.dist-info/RECORD
