Metadata-Version: 2.1
Name: pipeline-material
Version: 1.0
Summary: Pipeline material class for static integrity calculation
Home-page: https://github.com/vb64/pipeline.material
Author: Vitaly Bogomolov
Author-email: mail@vitaly-bogomolov.ru
Project-URL: Bug Tracker, https://github.com/vb64/pipeline.material/issues
Classifier: Programming Language :: Python
Classifier: License :: OSI Approved :: MIT License
Classifier: Operating System :: OS Independent
License-File: LICENSE
